bcdi/__init__.py
bcdi/constants.py
bcdi/algorithms/__init__.py
bcdi/algorithms/algorithms_utils.py
bcdi/examples/ID27_config_preprocessing_cdi.yml
bcdi/examples/S11_config_postprocessing.yml
bcdi/examples/S11_config_preprocessing.yml
bcdi/examples/S11_modes_252_210_200_prebinning_1_2_2.h5
bcdi/examples/S11_modes_252_420_392_prebinning_1_1_1.h5
bcdi/examples/__init__.py
bcdi/experiment/__init__.py
bcdi/experiment/beamline.py
bcdi/experiment/beamline_factory.py
bcdi/experiment/detector.py
bcdi/experiment/diffractometer.py
bcdi/experiment/loader.py
bcdi/experiment/rotation_matrix.py
bcdi/experiment/setup.py
bcdi/graph/__init__.py
bcdi/graph/colormap.py
bcdi/graph/graph_utils.py
bcdi/graph/linecut.py
bcdi/graph/turbo_colormap.py
bcdi/postprocessing/__init__.py
bcdi/postprocessing/analysis.py
bcdi/postprocessing/facet_analysis.py
bcdi/postprocessing/facet_recognition.py
bcdi/postprocessing/postprocessing_runner.py
bcdi/postprocessing/postprocessing_utils.py
bcdi/postprocessing/process_scan.py
bcdi/postprocessing/raw_orthogonalization.py
bcdi/preprocessing/ReadNxs3.py
bcdi/preprocessing/__init__.py
bcdi/preprocessing/alias_dict_2018.txt
bcdi/preprocessing/alias_dict_2019.txt
bcdi/preprocessing/alias_dict_2020.txt
bcdi/preprocessing/alias_dict_2021.txt
bcdi/preprocessing/alias_dict_2022.txt
bcdi/preprocessing/analysis.py
bcdi/preprocessing/bcdi_utils.py
bcdi/preprocessing/cdi_utils.py
bcdi/preprocessing/center_fft.py
bcdi/preprocessing/nxsReady.py
bcdi/preprocessing/preprocessing_runner.py
bcdi/preprocessing/process_scan.py
bcdi/preprocessing/process_scan_cdi.py
bcdi/simulation/__init__.py
bcdi/simulation/simulation_utils.py
bcdi/simulation/supportMaker.py
bcdi/utils/__init__.py
bcdi/utils/constants.py
bcdi/utils/format.py
bcdi/utils/image_registration.py
bcdi/utils/io_helper.py
bcdi/utils/parameters.py
bcdi/utils/parser.py
bcdi/utils/snippets_logging.py
bcdi/utils/text.py
bcdi/utils/utilities.py
bcdi/utils/validation.py
bcdi/xcca/__init__.py
bcdi/xcca/xcca_utils.py
bcdi-0.3.1.dist-info/LICENSE.txt
bcdi-0.3.1.dist-info/METADATA
bcdi-0.3.1.dist-info/WHEEL
bcdi-0.3.1.dist-info/top_level.txt
bcdi-0.3.1.dist-info/RECORD
