Metadata-Version: 2.1
Name: bcdi
Version: 0.3.1
Summary: BCDI: tools for pre(post)-processing Bragg and
Home-page: https://github.com/carnisj/bcdi
Author: Jerome Carnis
Author-email: carnis_jerome@yahoo.fr
License: CeCILL-B
Project-URL: Documentation, https://bcdi.readthedocs.io/en/latest/
Keywords: BCDI Bragg coherent X-rays diffraction imaging
Classifier: Development Status :: 3 - Alpha
Classifier: Intended Audience :: Science/Research
Classifier: Topic :: Scientific/Engineering :: Physics
Classifier: Topic :: Software Development :: Libraries :: Python Modules
Classifier: License :: CeCILL-B Free Software License Agreement (CECILL-B)
Classifier: Programming Language :: Python :: 3.8
Classifier: Programming Language :: Python :: 3.9
Classifier: Programming Language :: Python :: 3.10
Classifier: Operating System :: OS Independent
Requires-Python: >=3.8, <3.11
License-File: LICENSE.txt
Requires-Dist: colorcet (==3.0.1)
Requires-Dist: fabio (==2022.12.1)
Requires-Dist: hdf5plugin (==4.1.1)
Requires-Dist: h5py (==3.8.0)
Requires-Dist: importlib-resources (==5.12.0)
Requires-Dist: ipywidgets (==8.0.4)
Requires-Dist: lmfit (==1.1.0)
Requires-Dist: matplotlib (==3.7.1)
Requires-Dist: moviepy (==1.0.3)
Requires-Dist: numpy (==1.24.2)
Requires-Dist: pandas (==1.5.3)
Requires-Dist: pillow (==9.4.0)
Requires-Dist: pyqt5 (==5.15.9)
Requires-Dist: pyyaml (==6.0)
Requires-Dist: scikit-image (==0.20.0)
Requires-Dist: scipy (==1.9.1)
Requires-Dist: silx (==1.1.2)
Requires-Dist: tables (==3.8.0)
Requires-Dist: traits (==6.4.1)
Requires-Dist: vtk (==9.2.6)
Requires-Dist: xrayutilities (==1.7.4)
Provides-Extra: dev
Requires-Dist: black (==23.1.0) ; extra == 'dev'
Requires-Dist: coverage (==7.2.2) ; extra == 'dev'
Requires-Dist: doit (==0.36.0) ; extra == 'dev'
Requires-Dist: isort (==5.12.0) ; extra == 'dev'
Requires-Dist: mypy (==1.1.1) ; extra == 'dev'
Requires-Dist: pycodestyle (==2.10.0) ; extra == 'dev'
Requires-Dist: pydocstyle (==6.3.0) ; extra == 'dev'
Requires-Dist: pyfakefs (==5.1.0) ; extra == 'dev'
Requires-Dist: twine (==4.0.2) ; extra == 'dev'
Requires-Dist: wheel (==0.40.0) ; extra == 'dev'
Provides-Extra: doc
Requires-Dist: sphinx (==6.1.3) ; extra == 'doc'
Requires-Dist: sphinxcontrib-mermaid (==0.8.1) ; extra == 'doc'
